[{"資料來源(部會單位)": "臺灣花蓮地方法院", "資料集名稱": "公告臺灣花蓮地方法院104年度預算案(xml)", "下載次數": "28", "瀏覽次數": "875", "主要欄位": "歲入來源別預算表、歲出機關別預算表、歲入項目說明提要表、歲出計畫提要及分支計畫概況表、各項費用彙計表、歲出用途別科目分析表、資本支出分析表、人事費用分析表、預算員額明細表、公務車輛明細表、辦公房舍明細表、捐助經費分析表、歲出按職能及經濟性綜合分類表、委辦經費分析表", "編號": 1, "第一層級": "花蓮縣政府"}, {"資料來源(部會單位)": "臺灣花蓮地方法院", "資料集名稱": "公告臺灣花蓮地方法院104年度單位法定預算(xml)", "下載次數": "27", "瀏覽次數": "637", "主要欄位": "歲入來源別預算表、歲出機關別預算表、歲入項目說明提要表、歲出計畫提要及分支計畫概況表、各項費用彙計表、歲出用途別科目分析表、資本支出分析表、人事費用分析表、預算員額明細表、公務車輛明細表、辦公房舍明細表、捐助經費分析表、歲出按職能及經濟性綜合分類表、委辦經費分析表", "編號": 2, "第一層級": "花蓮縣政府"}, {"資料來源(部會單位)": "臺灣高等法院花蓮分院", "資料集名稱": "臺灣高等法院花蓮分院104年度預算案及法定預算 ", "下載次數": "37", "瀏覽次數": "822", "主要欄位": "歲入來源別預算表、歲出機關別預算表、歲入項目說明提要表、歲出計畫提要及分支計畫概況表、各項費用彙計表、歲出用途別科目分析表、資本支出分析表、人事費用分析表、預算員額明細表、公務車輛明細表、辦公房舍明細表、捐助經費分析表、歲出按職能及經濟性綜合分類表", "編號": 3, "第一層級": "花蓮縣政府"}, {"資料來源(部會單位)": "臺灣花蓮地方法院", "資料集名稱": "公告臺灣花蓮地方法院103年度決算書表(xml)檔", "下載次數": "25", "瀏覽次數": "719", "主要欄位": "歲入來源別決算表等8張書表", "編號": 4, "第一層級": "花蓮縣政府"}, {"資料來源(部會單位)": "臺灣花蓮地方法院", "資料集名稱": "公告臺灣花蓮地方法院104年1-5月會計月報(xml)檔", "下載次數": "36", "瀏覽次數": "961", "主要欄位": "104年1-5月會計月報檔(xml)", "編號": 5, "第一層級": "花蓮縣政府"}, {"資料來源(部會單位)": "臺灣花蓮地方法院", "資料集名稱": "公告臺灣花蓮地方法院104年6月會計月報(xml)檔", "下載次數": "24", "瀏覽次數": "627", "主要欄位": "經費類平衡表等8張表報", "編號": 6, "第一層級": "花蓮縣政府"}, {"資料來源(部會單位)": "臺灣高等法院花蓮分院", "資料集名稱": "臺灣高等法院花蓮分院103年度單位決算", "下載次數": "36", "瀏覽次數": "1146", "主要欄位": "臺灣高等法院花蓮分院公告本院103年度單位決算書表", "編號": 7, "第一層級": "花蓮縣政府"}, {"資料來源(部會單位)": "臺灣高等法院花蓮分院", "資料集名稱": "臺灣高等法院花蓮分院104年度1-6月份會計月報", "下載次數": "39", "瀏覽次數": "1202", "主要欄位": "臺灣高等法院花蓮分院公告本院104年度1-6月份會計月報檔(XML)", "編號": 8, "第一層級": "花蓮縣政府"}, {"資料來源(部會單位)": "臺灣高等法院花蓮分院", "資料集名稱": "臺灣高等法院花蓮分院104年度7月份會計月報", "下載次數": "97", "瀏覽次數": "488", "主要欄位": "臺灣高等法院花蓮分院104年度7月份會計月報", "編號": 9, "第一層級": "花蓮縣政府"}, {"資料來源(部會單位)": "臺灣花蓮地方法院", "資料集名稱": "臺灣花蓮地方法院104年7月會計月報(XML)檔", "下載次數": "7", "瀏覽次數": "489", "主要欄位": "歲入類平衡表等8張表報", "編號": 10, "第一層級": "花蓮縣政府"}, {"資料來源(部會單位)": "臺灣花蓮地方法院", "資料集名稱": "公告臺灣花蓮地方法院105年度單位預算案(XML檔)", "下載次數": "15", "瀏覽次數": "759", "主要欄位": "歲入來源別預算表等13張表單", "編號": 11, "第一層級": "花蓮縣政府"}, {"資料來源(部會單位)": "臺灣高等法院花蓮分院", "資料集名稱": "臺灣高等法院花蓮分院105年度預算案", "下載次數": "114", "瀏覽次數": "670", "主要欄位": "臺灣高等法院花蓮分院105年度預算案", "編號": 12, "第一層級": "花蓮縣政府"}, {"資料來源(部會單位)": "臺灣花蓮地方法院", "資料集名稱": "公告臺灣花蓮地方法院104年8月會計月報(XML檔)", "下載次數": "13", "瀏覽次數": "837", "主要欄位": "歲入類平衡表等8張表單", "編號": 13, "第一層級": "花蓮縣政府"}, {"資料來源(部會單位)": "臺灣高等法院花蓮分院", "資料集名稱": "臺灣高等法院花蓮分院104年度8月份會計月報", "下載次數": "16", "瀏覽次數": "829", "主要欄位": "臺灣高等法院花蓮分院104年度8月份會計月報", "編號": 14, "第一層級": "花蓮縣政府"}, {"資料來源(部會單位)": "臺灣高等法院花蓮分院", "資料集名稱": "臺灣高等法院花蓮分院104年度9月份會計月報", "下載次數": "19", "瀏覽次數": "637", "主要欄位": "臺灣高等法院花蓮分院104年度9月份會計月報", "編號": 15, "第一層級": "花蓮縣政府"}, {"資料來源(部會單位)": "臺灣花蓮地方法院", "資料集名稱": "公告本院104年9月會計月報(XML檔)", "下載次數": "11", "瀏覽次數": "415", "主要欄位": "經費類平衡表等8件表單", "編號": 16, "第一層級": "花蓮縣政府"}, {"資料來源(部會單位)": "臺灣高等法院花蓮分院", "資料集名稱": "臺灣高等法院花蓮分院104年度10月份會計月報", "下載次數": "16", "瀏覽次數": "483", "主要欄位": "臺灣高等法院花蓮分院104年度10月份會計月報", "編號": 17, "第一層級": "花蓮縣政府"}, {"資料來源(部會單位)": "臺灣花蓮地方法院", "資料集名稱": "公告臺灣花蓮地方法院104年10月會計月報(XML檔)", "下載次數": "20", "瀏覽次數": "476", "主要欄位": "歲入類平衡表等表單", "編號": 18, "第一層級": "花蓮縣政府"}, {"資料來源(部會單位)": "花蓮縣政府", "資料集名稱": "花蓮縣老樹地圖", "下載次數": "145", "瀏覽次數": "1633", "主要欄位": "於地圖上顯示花蓮縣境內各鄉鎮老樹所在位置", "編號": 19, "第一層級": "花蓮縣政府"}, {"資料來源(部會單位)": "臺灣高等法院花蓮分院", "資料集名稱": "臺灣高等法院花蓮分院104年度11月份會計月報", "下載次數": "8", "瀏覽次數": "512", "主要欄位": "臺灣高等法院花蓮分院104年度11月份會計月報", "編號": 20, "第一層級": "花蓮縣政府"}, {"資料來源(部會單位)": "臺灣花蓮地方法院", "資料集名稱": "公告臺灣花蓮地方法院104年11月會計報告(XML檔)", "下載次數": "14", "瀏覽次數": "519", "主要欄位": "歲入類平衡表等8張表單", "編號": 21, "第一層級": "花蓮縣政府"}, {"資料來源(部會單位)": "臺灣高等法院花蓮分院", "資料集名稱": "臺灣高等法院花蓮分院104年度12月份會計月報", "下載次數": "6", "瀏覽次數": "339", "主要欄位": "臺灣高等法院花蓮分院104年度12月份會計月報", "編號": 22, "第一層級": "花蓮縣政府"}, {"資料來源(部會單位)": "臺灣高等法院花蓮分院", "資料集名稱": "臺灣高等法院花蓮分院105年度單位預算", "下載次數": "11", "瀏覽次數": "573", "主要欄位": "臺灣高等法院花蓮分院105年度單位預算", "編號": 23, "第一層級": "花蓮縣政府"}, {"資料來源(部會單位)": "臺灣花蓮地方法院", "資料集名稱": "公告臺灣花蓮地方法院104年12月會計月報(XML檔)", "下載次數": "9", "瀏覽次數": "463", "主要欄位": "歲入類平衡表等8張表單", "編號": 24, "第一層級": "花蓮縣政府"}, {"資料來源(部會單位)": "臺灣花蓮地方法院", "資料集名稱": "公告臺灣花蓮地方法院105年度法定預算(XML檔)", "下載次數": "83", "瀏覽次數": "473", "主要欄位": "歲入來源別預算表等表件", "編號": 25, "第一層級": "花蓮縣政府"}, {"資料來源(部會單位)": "臺灣花蓮地方法院", "資料集名稱": "公告臺灣花蓮地方法院105年1月會計報告(xml檔)", "下載次數": "16", "瀏覽次數": "393", "主要欄位": "平衡表等6表單", "編號": 26, "第一層級": "花蓮縣政府"}, {"資料來源(部會單位)": "臺灣高等法院花蓮分院", "資料集名稱": "臺灣高等法院花蓮分院105年度1月份會計月報", "下載次數": "8", "瀏覽次數": "396", "主要欄位": "會計月報2張：經費累計表、歲入累計表", "編號": 27, "第一層級": "花蓮縣政府"}, {"資料來源(部會單位)": "臺灣高等法院花蓮分院", "資料集名稱": "臺灣高等法院花蓮分院公告本院104年度單位決算", "下載次數": "9", "瀏覽次數": "388", "主要欄位": "單位決算書表5張：歲入來源別決算表、歲出政事別決算表、歲出機關別決算表、歲入類平衡表、經費類平衡表", "編號": 28, "第一層級": "花蓮縣政府"}, {"資料來源(部會單位)": "臺灣高等法院花蓮分院", "資料集名稱": "臺灣高等法院花蓮分院105年度2月份會計月報", "下載次數": "10", "瀏覽次數": "366", "主要欄位": "臺灣高等法院花蓮分院105年度2月份會計月報", "編號": 29, "第一層級": "花蓮縣政府"}, {"資料來源(部會單位)": "花蓮縣衛生局", "資料集名稱": "105年花蓮哺集乳室名單", "下載次數": "26", "瀏覽次數": "282", "主要欄位": "地址電話開放時間", "編號": 30, "第一層級": "花蓮縣政府"}, {"資料來源(部會單位)": "臺灣花蓮地方法院", "資料集名稱": "公告臺灣花蓮地方法院105年2月會計月報(xml檔)", "下載次數": "9", "瀏覽次數": "361", "主要欄位": "歲入累計表等4表件", "編號": 31, "第一層級": "花蓮縣政府"}, {"資料來源(部會單位)": "臺灣花蓮地方法院", "資料集名稱": "公告臺灣花蓮地方法院104年度單位決算(XML檔)", "下載次數": "13", "瀏覽次數": "344", "主要欄位": "歲入來源別決算書等8表件", "編號": 32, "第一層級": "花蓮縣政府"}, {"資料來源(部會單位)": "臺灣高等法院花蓮分院", "資料集名稱": "臺灣高等法院花蓮分院105年度3月份會計月報", "下載次數": "9", "瀏覽次數": "372", "主要欄位": "臺灣高等法院花蓮分院105年度3月份會計月報", "編號": 33, "第一層級": "花蓮縣政府"}, {"資料來源(部會單位)": "臺灣花蓮地方法院", "資料集名稱": "公告臺灣花蓮地方法院105年3月會計月報(XML檔)", "下載次數": "8", "瀏覽次數": "316", "主要欄位": "歲入累計表", "編號": 34, "第一層級": "花蓮縣政府"}, {"資料來源(部會單位)": "臺灣高等法院花蓮分院", "資料集名稱": "臺灣高等法院花蓮分院105年度4月份會計月報", "下載次數": "5", "瀏覽次數": "423", "主要欄位": "會計月報3張：歲入累計表、經費累計表、平衡表", "編號": 35, "第一層級": "花蓮縣政府"}, {"資料來源(部會單位)": "臺灣花蓮地方法院", "資料集名稱": "公告臺灣花蓮地方法院105年4月會計月報(XML檔)", "下載次數": "10", "瀏覽次數": "314", "主要欄位": "歲入累計表等表件", "編號": 36, "第一層級": "花蓮縣政府"}, {"資料來源(部會單位)": "臺灣花蓮地方法院", "資料集名稱": "重新公告臺灣花蓮地方法院105年1月會計月報(XML檔)", "下載次數": "9", "瀏覽次數": "369", "主要欄位": "歲入累計表等表件", "編號": 37, "第一層級": "花蓮縣政府"}, {"資料來源(部會單位)": "臺灣花蓮地方法院", "資料集名稱": "重新公告臺灣花蓮地方法院105年2月會計月報(XML檔)", "下載次數": "6", "瀏覽次數": "316", "主要欄位": "歲入累計表等表件", "編號": 38, "第一層級": "花蓮縣政府"}, {"資料來源(部會單位)": "臺灣花蓮地方法院", "資料集名稱": "重新公告臺灣花蓮地方法院105年3月會計月報(XML檔)", "下載次數": "7", "瀏覽次數": "313", "主要欄位": "歲入累計表等表件", "編號": 39, "第一層級": "花蓮縣政府"}, {"資料來源(部會單位)": "臺灣花蓮地方法院", "資料集名稱": "重新公告臺灣花蓮地方法院105年4月會計月報(XML檔)", "下載次數": "8", "瀏覽次數": "347", "主要欄位": "歲入累計表等表件", "編號": 40, "第一層級": "花蓮縣政府"}, {"資料來源(部會單位)": "臺灣花蓮地方法院", "資料集名稱": "公告臺灣花蓮地方法院105年5月會計月報(XML檔)", "下載次數": "7", "瀏覽次數": "332", "主要欄位": "歲入累計表等表件", "編號": 41, "第一層級": "花蓮縣政府"}, {"資料來源(部會單位)": "臺灣高等法院花蓮分院", "資料集名稱": "臺灣高等法院花蓮分院105年度6月份會計月報", "下載次數": "6", "瀏覽次數": "273", "主要欄位": "臺灣高等法院花蓮分院105年度6月份會計月報", "編號": 42, "第一層級": "花蓮縣政府"}, {"資料來源(部會單位)": "臺灣高等法院花蓮分院", "資料集名稱": "臺灣高等法院花蓮分院105年度5月份會計月報", "下載次數": "8", "瀏覽次數": "282", "主要欄位": "臺灣高等法院花蓮分院105年度5月份會計月報", "編號": 43, "第一層級": "花蓮縣政府"}, {"資料來源(部會單位)": "臺灣花蓮地方法院", "資料集名稱": "公告臺灣花蓮地方法院105年6月會計月報(XML檔)", "下載次數": "5", "瀏覽次數": "251", "主要欄位": "歲入累計表等13表件", "編號": 44, "第一層級": "花蓮縣政府"}, {"資料來源(部會單位)": "臺灣花蓮地方法院", "資料集名稱": "公告臺灣花蓮地方法院105年7月會計月報(XML檔)", "下載次數": "9", "瀏覽次數": "267", "主要欄位": "歲入累計表等13表件", "編號": 45, "第一層級": "花蓮縣政府"}, {"資料來源(部會單位)": "臺灣花蓮地方法院", "資料集名稱": "公告臺灣花蓮地方法院106年度單位預算案(XML檔)", "下載次數": "13", "瀏覽次數": "293", "主要欄位": "歲入來源別預算表等13表件", "編號": 46, "第一層級": "花蓮縣政府"}, {"資料來源(部會單位)": "臺灣高等法院花蓮分院", "資料集名稱": "臺灣高等法院花蓮分院106年度預算案", "下載次數": "15", "瀏覽次數": "421", "主要欄位": "臺灣高等法院花蓮分院106年度預算案", "編號": 47, "第一層級": "花蓮縣政府"}, {"資料來源(部會單位)": "臺灣高等法院花蓮分院", "資料集名稱": " 臺灣高等法院花蓮分院105年度7月份會計月報", "下載次數": "5", "瀏覽次數": "230", "主要欄位": "臺灣高等法院花蓮分院105年度7月份會計月報", "編號": 48, "第一層級": "花蓮縣政府"}, {"資料來源(部會單位)": "臺灣高等法院花蓮分院", "資料集名稱": "臺灣高等法院花蓮分院105年度8月份會計月報", "下載次數": "7", "瀏覽次數": "283", "主要欄位": "臺灣高等法院花蓮分院105年度8月份會計月報", "編號": 49, "第一層級": "花蓮縣政府"}, {"資料來源(部會單位)": "臺灣花蓮地方法院", "資料集名稱": "公告臺灣花蓮地方法院105年8月會計月報(XML檔)", "下載次數": "3", "瀏覽次數": "275", "主要欄位": "歲入累計表等13表件", "編號": 50, "第一層級": "花蓮縣政府"}, {"資料來源(部會單位)": "臺灣花蓮地方法院", "資料集名稱": "公告臺灣花蓮地方法院104年度單位決算(院修版)(XML檔)", "下載次數": "5", "瀏覽次數": "234", "主要欄位": "歲入來源別決算表等8表件", "編號": 51, "第一層級": "花蓮縣政府"}, {"資料來源(部會單位)": "臺灣花蓮地方法院", "資料集名稱": "公告臺灣花蓮地方法院105年9月份會計月報(XML檔)", "下載次數": "10", "瀏覽次數": "162", "主要欄位": "歲入累計表等13表件", "編號": 52, "第一層級": "花蓮縣政府"}, {"資料來源(部會單位)": "臺灣高等法院花蓮分院", "資料集名稱": "臺灣高等法院花蓮分院105年度9月份會計月報", "下載次數": "7", "瀏覽次數": "186", "主要欄位": "臺灣高等法院花蓮分院105年度9月份會計月報", "編號": 53, "第一層級": "花蓮縣政府"}, {"資料來源(部會單位)": "臺灣高等法院花蓮分院", "資料集名稱": "臺灣高等法院花蓮分院105年度10月份會計月報", "下載次數": "0", "瀏覽次數": "39", "主要欄位": "臺灣高等法院花蓮分院105年度10月份會計月報", "編號": 54, "第一層級": "花蓮縣政府"}, {"資料來源(部會單位)": "臺灣花蓮地方法院", "資料集名稱": "公告臺灣花蓮地方法院105年10月份會計月報(XML檔)", "下載次數": "0", "瀏覽次數": "66", "主要欄位": "歲入累計表等13表件", "編號": 55, "第一層級": "花蓮縣政府"}, {"資料來源(部會單位)": "臺灣高等法院花蓮分院", "資料集名稱": "臺灣高等法院花蓮分院105年度11月份會計月報", "下載次數": "0", "瀏覽次數": "48", "主要欄位": "臺灣高等法院花蓮分院105年度11月份會計月報", "編號": 56, "第一層級": "花蓮縣政府"}, {"資料來源(部會單位)": "臺灣花蓮地方法院", "資料集名稱": "公告臺灣花蓮地方法院105年11月份會計月報(XML檔)", "下載次數": "0", "瀏覽次數": "51", "主要欄位": "歲入累計表等13表件", "編號": 57, "第一層級": "花蓮縣政府"}, {"資料來源(部會單位)": "花蓮縣消防局", "資料集名稱": "花蓮縣七星潭風景區告示牌及救生圈現況", "下載次數": "5", "瀏覽次數": "138", "主要欄位": "項次    地點    設置救生圈1新城分局前直行約1公里右轉入灘路口2&quot;新城鐵馬19K+400處，石座椅旁秀林國中旁&quot;3&quot;新城海堤，下灘樓梯左邊突出海堤新城鄉博愛路底，門牌號為中山路46-18號秀林國中旁&quot;4新城海堤向南第一處斜坡5新城海堤向南第二處斜坡6草林安檢所7花草集民宿前8東潤安檢所9193縣道，２K+100七星媽宮廟10沙東露營區欄杆破口處11沙東露營區12林語亭13德燕漁場停車場■14德燕漁場停車場兩潭自行車道100M■15航道下廁所■16航道下廁所樓梯■17七星潭下灘處■18七星潭下灘處■19七星潭下灘處■20七星潭下灘處■21七星潭下灘處■22七星潭下灘處■23賞星廣場大排護欄■24賞星廣場大排護欄■25臨潭橋左側■26臨潭橋右側■27七星安檢所■28七星潭旅客服務中心後方■29船型廁所後方■30望海樓停車場■31望海樓停車場-拍岸亭■(■代表有)", "編號": 58, "第一層級": "花蓮縣政府"}, {"資料來源(部會單位)": "花蓮縣消防局", "資料集名稱": "花蓮縣較常發生溺水案件水域一覽表", "下載次數": "5", "瀏覽次數": "95", "主要欄位": "編號地點鄰近分隊1立霧溪新秀分隊2三棧溪北埔分隊3七星潭美崙分隊4美崙溪花蓮分隊5花蓮溪出海口仁里分隊6國姓廟出海口仁里分隊7水源地自強分隊8木瓜溪壽豐分隊9豐濱海域豐濱分隊10磯崎海域豐濱分隊11芭崎海域豐濱分隊12鹽寮海域豐濱分隊13石梯坪豐濱分隊14萬里溪萬榮分隊15鯉魚潭壽豐分隊16崇德海域新秀分隊17慕谷慕魚壽豐分隊", "編號": 59, "第一層級": "花蓮縣政府"}, {"資料來源(部會單位)": "臺灣花蓮地方法院", "資料集名稱": "公告臺灣花蓮地方法院105年12月份會計月報(XML檔)", "下載次數": "0", "瀏覽次數": "36", "主要欄位": "歲入累計表等13表件", "編號": 60, "第一層級": "花蓮縣政府"}, {"資料來源(部會單位)": "臺灣高等法院花蓮分院", "資料集名稱": "臺灣高等法院花蓮分院105年度12月份會計月報", "下載次數": "0", "瀏覽次數": "42", "主要欄位": "臺灣高等法院花蓮分院105年度12月份會計月報", "編號": 61, "第一層級": "花蓮縣政府"}, {"資料來源(部會單位)": "臺灣高等法院花蓮分院", "資料集名稱": "臺灣高等法院花蓮分院106年度01月份會計月報", "下載次數": "0", "瀏覽次數": "73", "主要欄位": "臺灣高等法院花蓮分院106年度01月份會計月報", "編號": 62, "第一層級": "花蓮縣政府"}, {"資料來源(部會單位)": "臺灣花蓮地方法院", "資料集名稱": "公告臺灣花蓮地方法院106年1月份會計月報(XML檔)", "下載次數": "1", "瀏覽次數": "47", "主要欄位": "歲入累計表等13表件", "編號": 63, "第一層級": "花蓮縣政府"}, {"資料來源(部會單位)": "臺灣高等法院花蓮分院", "資料集名稱": "臺灣高等法院花蓮分院106年度02月份會計月報", "下載次數": "0", "瀏覽次數": "87", "主要欄位": "臺灣高等法院花蓮分院106年度02月份會計月報", "編號": 64, "第一層級": "花蓮縣政府"}, {"資料來源(部會單位)": "臺灣花蓮地方法院", "資料集名稱": "公告臺灣花蓮地方法院106年度法定預算(XML檔)", "下載次數": "0", "瀏覽次數": "72", "主要欄位": "人事費分析表等13表件", "編號": 65, "第一層級": "花蓮縣政府"}, {"資料來源(部會單位)": "臺灣高等法院花蓮分院", "資料集名稱": "臺灣高等法院花蓮分院106年度單位預算", "下載次數": "1", "瀏覽次數": "60", "主要欄位": "臺灣高等法院花蓮分院106年度單位預算", "編號": 66, "第一層級": "花蓮縣政府"}, {"資料來源(部會單位)": "臺灣花蓮地方法院", "資料集名稱": "公告臺灣花蓮地方法院106年2月份會計月報(XML檔)", "下載次數": "0", "瀏覽次數": "40", "主要欄位": "歲入累計表等13表件", "編號": 67, "第一層級": "花蓮縣政府"}, {"資料來源(部會單位)": "花蓮縣消防局", "資料集名稱": "補助團體私人報表", "下載次數": "3", "瀏覽次數": "63", "主要欄位": "工作計畫名稱、補助事項或用途及補助對象", "編號": 68, "第一層級": "花蓮縣政府"}, {"資料來源(部會單位)": "臺灣高等法院花蓮分院", "資料集名稱": "臺灣高等法院花蓮分院106年度3月份會計月報", "下載次數": "0", "瀏覽次數": "53", "主要欄位": "臺灣高等法院花蓮分院106年度3月份會計月報", "編號": 69, "第一層級": "花蓮縣政府"}, {"資料來源(部會單位)": "臺灣花蓮地方法院", "資料集名稱": "公告臺灣花蓮地方法院106年3月份會計月報(xml檔)", "下載次數": "0", "瀏覽次數": "44", "主要欄位": "歲入累計表等13表件", "編號": 70, "第一層級": "花蓮縣政府"}, {"資料來源(部會單位)": "臺灣花蓮地方法院", "資料集名稱": "公告臺灣花蓮地方法院105年度單位決算(XML檔)", "下載次數": "2", "瀏覽次數": "69", "主要欄位": "歲入來源別決算表等13表件", "編號": 71, "第一層級": "花蓮縣政府"}, {"資料來源(部會單位)": "臺灣高等法院花蓮分院", "資料集名稱": "臺灣高等法院花蓮分院105年度單位決算", "下載次數": "0", "瀏覽次數": "36", "主要欄位": "臺灣高等法院花蓮分院105年度單位決算", "編號": 72, "第一層級": "花蓮縣政府"}, {"資料來源(部會單位)": "臺灣高等法院花蓮分院", "資料集名稱": "臺灣高等法院花蓮分院106年度4月份會計月報", "下載次數": "0", "瀏覽次數": "52", "主要欄位": "臺灣高等法院花蓮分院106年度4月份會計月報", "編號": 73, "第一層級": "花蓮縣政府"}, {"資料來源(部會單位)": "臺灣花蓮地方法院", "資料集名稱": "公告臺灣花蓮地方法院106年4月份會計月報(XML檔)", "下載次數": "2", "瀏覽次數": "66", "主要欄位": "歲入累計表等13表建", "編號": 74, "第一層級": "花蓮縣政府"}, {"資料來源(部會單位)": "臺灣高等法院花蓮分院", "資料集名稱": "臺灣高等法院花蓮分院106年度05月份會計月報", "下載次數": "0", "瀏覽次數": "48", "主要欄位": "臺灣高等法院花蓮分院106年度5月份會計月報", "編號": 75, "第一層級": "花蓮縣政府"}, {"資料來源(部會單位)": "臺灣花蓮地方法院", "資料集名稱": "公告臺灣花蓮地方法院106年5月份會計月報(XML檔)", "下載次數": "0", "瀏覽次數": "50", "主要欄位": "歲入累計表等13表件", "編號": 76, "第一層級": "花蓮縣政府"}, {"資料來源(部會單位)": "臺灣高等法院花蓮分院", "資料集名稱": "臺灣高等法院花蓮分院106年度6月份會計月報", "下載次數": "0", "瀏覽次數": "48", "主要欄位": "臺灣高等法院花蓮分院106年度6月份會計月報", "編號": 77, "第一層級": "花蓮縣政府"}, {"資料來源(部會單位)": "臺灣花蓮地方法院", "資料集名稱": "公告臺灣花蓮地方法院106年6月份會計月報(XML檔)", "下載次數": "1", "瀏覽次數": "54", "主要欄位": "歲入累計表等13表建", "編號": 78, "第一層級": "花蓮縣政府"}, {"資料來源(部會單位)": "臺灣高等法院花蓮分院", "資料集名稱": "臺灣高等法院花蓮分院106年度7月份會計月報", "下載次數": "1", "瀏覽次數": "72", "主要欄位": "臺灣高等法院花蓮分院106年度7月份會計月報", "編號": 79, "第一層級": "花蓮縣政府"}, {"資料來源(部會單位)": "臺灣花蓮地方法院", "資料集名稱": "公告臺灣花蓮地方法院106年7月份會計月報(XML檔)", "下載次數": "1", "瀏覽次數": "90", "主要欄位": "", "編號": 80, "第一層級": "花蓮縣政府"}, {"資料來源(部會單位)": "臺灣花蓮地方法院", "資料集名稱": "公告臺灣花蓮地方法院107年度預算案書(XML檔)", "下載次數": "5", "瀏覽次數": "74", "主要欄位": "", "編號": 81, "第一層級": "花蓮縣政府"}, {"資料來源(部會單位)": "臺灣高等法院花蓮分院", "資料集名稱": "臺灣高等法院花蓮分院107年度預算案(XML)", "下載次數": "3", "瀏覽次數": "78", "主要欄位": "", "編號": 82, "第一層級": "花蓮縣政府"}, {"資料來源(部會單位)": "臺灣高等法院花蓮分院", "資料集名稱": "臺灣高等法院花蓮分院106年度8月份會計月報(XML)", "下載次數": "0", "瀏覽次數": "86", "主要欄位": "", "編號": 83, "第一層級": "花蓮縣政府"}, {"資料來源(部會單位)": "臺灣花蓮地方法院", "資料集名稱": "公告臺灣花蓮地方法院106年8月份會計月報(XML檔)", "下載次數": "1", "瀏覽次數": "65", "主要欄位": "", "編號": 84, "第一層級": "花蓮縣政府"}, {"資料來源(部會單位)": "臺灣高等法院花蓮分院", "資料集名稱": "臺灣高等法院花蓮分院106年度9月份會計月報(XML)", "下載次數": "1", "瀏覽次數": "46", "主要欄位": "", "編號": 85, "第一層級": "花蓮縣政府"}, {"資料來源(部會單位)": "臺灣花蓮地方法院", "資料集名稱": "公告臺灣花蓮地方法院106年9月份會計月報(XML檔)", "下載次數": "0", "瀏覽次數": "38", "主要欄位": "", "編號": 86, "第一層級": "花蓮縣政府"}, {"資料來源(部會單位)": "臺灣高等法院花蓮分院", "資料集名稱": "臺灣高等法院花蓮分院106年度10月份會計月報(XML)", "下載次數": "1", "瀏覽次數": "45", "主要欄位": "", "編號": 87, "第一層級": "花蓮縣政府"}, {"資料來源(部會單位)": "臺灣花蓮地方法院", "資料集名稱": "公告臺灣花蓮地方法院106年10月份會計月報(XML檔)", "下載次數": "0", "瀏覽次數": "38", "主要欄位": "", "編號": 88, "第一層級": "花蓮縣政府"}, {"資料來源(部會單位)": "臺灣高等法院花蓮分院", "資料集名稱": "臺灣高等法院花蓮分院106年度11月份會計月報(XML)", "下載次數": "0", "瀏覽次數": "36", "主要欄位": "", "編號": 89, "第一層級": "花蓮縣政府"}, {"資料來源(部會單位)": "臺灣花蓮地方法院", "資料集名稱": "公告臺灣花蓮地方法院106年11月份會計月報(XML檔)", "下載次數": "1", "瀏覽次數": "32", "主要欄位": "", "編號": 90, "第一層級": "花蓮縣政府"}, {"資料來源(部會單位)": "花蓮縣政府", "資料集名稱": "花蓮縣公立殯葬設施資訊", "下載次數": "6", "瀏覽次數": "87", "主要欄位": "公所名稱,殯葬設施,聯絡電話,備註", "編號": 91, "第一層級": "花蓮縣政府"}, {"資料來源(部會單位)": "花蓮縣政府", "資料集名稱": "花蓮縣歷次停班停課訊息一覽表", "下載次數": "21", "瀏覽次數": "198", "主要欄位": "日期,星期,地區,是否停止上班上課情形", "編號": 92, "第一層級": "花蓮縣政府"}, {"資料來源(部會單位)": "花蓮縣政府", "資料集名稱": "花蓮縣政府及所屬一、二級機關編制員額數", "下載次數": "34", "瀏覽次數": "202", "主要欄位": "花蓮縣政府及所屬一、二級機關名稱,機關編制員額數", "編號": 93, "第一層級": "花蓮縣政府"}, {"資料來源(部會單位)": "花蓮縣政府", "資料集名稱": "花蓮縣政府員工特約商店", "下載次數": "23", "瀏覽次數": "120", "主要欄位": "店家名稱,折數,電話,地址", "編號": 94, "第一層級": "花蓮縣政府"}, {"資料來源(部會單位)": "花蓮縣政府", "資料集名稱": "花蓮縣政府商業登記資訊系統商業設立登記清冊", "下載次數": "26", "瀏覽次數": "163", "主要欄位": "統一編號,商業名稱,主營業項目", "編號": 95, "第一層級": "花蓮縣政府"}, {"資料來源(部會單位)": "花蓮縣政府", "資料集名稱": "花蓮縣消防局較常執行溺水事件救援地點清冊", "下載次數": "3", "瀏覽次數": "44", "主要欄位": "編號,地點,鄰近分隊", "編號": 96, "第一層級": "花蓮縣政府"}, {"資料來源(部會單位)": "花蓮縣政府", "資料集名稱": "花蓮縣iTaiwan WI-FI無線上網地圖", "下載次數": "127", "瀏覽次數": "405", "主要欄位": "主管機關,熱點名稱,地址,緯度,經度", "編號": 97, "第一層級": "花蓮縣政府"}, {"資料來源(部會單位)": "花蓮縣政府", "資料集名稱": "花蓮縣應回收廢棄物回收處理業者名冊", "下載次數": "4", "瀏覽次數": "57", "主要欄位": "類別,類型,編號,商店名稱,統一編號,貯存地址,登記地址", "編號": 98, "第一層級": "花蓮縣政府"}, {"資料來源(部會單位)": "花蓮縣政府", "資料集名稱": "花蓮縣政府暨相關機關名錄", "下載次數": "6", "瀏覽次數": "63", "主要欄位": "序,機關名稱,地址,電話,傳真,網址", "編號": 99, "第一層級": "花蓮縣政府"}, {"資料來源(部會單位)": "花蓮縣政府", "資料集名稱": "花蓮縣政府辦理「縣長親民時間」日期一覽表", "下載次數": "2", "瀏覽次數": "46", "主要欄位": "場次,日期時間,鄉鎮市,地點", "編號": 100, "第一層級": "花蓮縣政府"}, {"資料來源(部會單位)": "花蓮縣政府", "資料集名稱": "花蓮縣政府雙語辭彙對照表", "下載次數": "4", "瀏覽次數": "37", "主要欄位": "主題,詞彙,翻譯", "編號": 101, "第一層級": "花蓮縣政府"}, {"資料來源(部會單位)": "花蓮縣政府", "資料集名稱": "花蓮縣消防局各大隊、分隊地址及聯絡電話", "下載次數": "13", "瀏覽次數": "102", "主要欄位": "消防局各大隊、分隊,室內電話,警用電話,傳真號碼,地址", "編號": 102, "第一層級": "花蓮縣政府"}, {"資料來源(部會單位)": "花蓮縣政府", "資料集名稱": "花蓮縣各鄉鎮市災害應變中心聯絡電話", "下載次數": "9", "瀏覽次數": "106", "主要欄位": "單位,聯絡方式,傳真", "編號": 103, "第一層級": "花蓮縣政府"}, {"資料來源(部會單位)": "花蓮縣政府", "資料集名稱": "花蓮縣警察局單位執掌與聯繫表", "下載次數": "9", "瀏覽次數": "55", "主要欄位": "單位,住址,電話", "編號": 104, "第一層級": "花蓮縣政府"}, {"資料來源(部會單位)": "花蓮縣政府", "資料集名稱": "花蓮縣政府對民間團體補(捐)助經費明細表", "下載次數": "3", "瀏覽次數": "56", "主要欄位": "工作計畫科目名稱,補助事項或用途,補助對象,主辦機關,累計撥付金額(單位：千元)、,有無涉及財物或勞務採購,處理方式(如未涉及採購則毋須填列，如採公開招標，請填列得標廠商)、,是否為除外規定民間團體", "編號": 105, "第一層級": "花蓮縣政府"}, {"資料來源(部會單位)": "花蓮縣政府", "資料集名稱": "花蓮縣全縣各鄉鎮人口統計表", "下載次數": "81", "瀏覽次數": "432", "主要欄位": "序號,年度,月份,鄉鎮別,戶數,人口數,男性人數,女性人數,平地原住民,山地原住民", "編號": 106, "第一層級": "花蓮縣政府"}, {"資料來源(部會單位)": "花蓮縣政府", "資料集名稱": "花蓮縣促進民間參與公共建設案件一覽表", "下載次數": "10", "瀏覽次數": "50", "主要欄位": "序號,案件名稱,主辦機關,規劃方式,公共建設類別,公共建設-細類別,民間參與方式,委託顧問廠商", "編號": 107, "第一層級": "花蓮縣政府"}, {"資料來源(部會單位)": "花蓮縣政府", "資料集名稱": "花蓮縣酒製造業者資料", "下載次數": "0", "瀏覽次數": "46", "主要欄位": "酒製造業資料,製造業者名稱,工廠地址,負責人,電話", "編號": 108, "第一層級": "花蓮縣政府"}, {"資料來源(部會單位)": "花蓮縣政府", "資料集名稱": "花蓮縣地方稅務局檔案閱覽抄錄複製收費標準", "下載次數": "2", "瀏覽次數": "44", "主要欄位": "檔案外觀型式,複製方式,複製格式,收費標準_以新臺幣計價,備註", "編號": 109, "第一層級": "花蓮縣政府"}, {"資料來源(部會單位)": "花蓮縣政府", "資料集名稱": "花蓮縣地方稅務局人民申請案件處理時限表", "下載次數": "1", "瀏覽次數": "42", "主要欄位": "機關名稱,申請類型,處理時限(天數)", "編號": 110, "第一層級": "花蓮縣政府"}, {"資料來源(部會單位)": "花蓮縣政府", "資料集名稱": "花蓮縣車輛使用別統計表", "下載次數": "2", "瀏覽次數": "40", "主要欄位": "機器行駛車輛,細稅目,應稅數_件數,應稅數_稅額,免稅數件數,稅額,徵起數_件數,徵起數_金額", "編號": 111, "第一層級": "花蓮縣政府"}, {"資料來源(部會單位)": "花蓮縣政府", "資料集名稱": "花蓮縣地方稅務局滯納及違章罰鍰移送執行情形月報表-稅別", "下載次數": "2", "瀏覽次數": "45", "主要欄位": "稅別,,1 上月止未結案,2 本 月 移 送,4 本月更正調整,6 本月徵起,7 本月取得憑證,8 本月撤案,9 本月退案,10 本月結案,11 本月清理合計,", "編號": 112, "第一層級": "花蓮縣政府"}, {"資料來源(部會單位)": "花蓮縣政府", "資料集名稱": "花蓮縣最近5年契稅綜合統計表", "下載次數": "3", "瀏覽次數": "39", "主要欄位": "年度別,件數應稅,件數免稅,契價應稅,契價免稅,稅額應稅,稅額免稅", "編號": 113, "第一層級": "花蓮縣政府"}, {"資料來源(部會單位)": "花蓮縣政府", "資料集名稱": "花蓮縣最近5年房屋稅綜合統計表", "下載次數": "4", "瀏覽次數": "41", "主要欄位": "項目/年度別,戶數合計,戶數應稅,戶數免稅,面積應稅,面積免稅,現值應稅,現值免稅,稅額合計,稅額本稅", "編號": 114, "第一層級": "花蓮縣政府"}, {"資料來源(部會單位)": "花蓮縣政府", "資料集名稱": "花蓮縣房屋標準單價表", "下載次數": "11", "瀏覽次數": "85", "主要欄位": "構造,鋼骨造P/ 鋼骨混凝土造A/ 鋼骨鋼筋混凝土造S,鋼骨造P/ 鋼骨混凝土造A/ 鋼骨鋼筋混凝土造S,鋼骨造P/ 鋼骨混凝土造A/ 鋼骨鋼筋混凝土造S,鋼骨造P/ 鋼骨混凝土造A/ 鋼骨鋼筋混凝土造S,鋼筋混凝土造B/預鑄混凝土造T,鋼筋混凝土造B/預鑄混凝土造T,鋼筋混凝土造B/預鑄混凝土造T,鋼筋混凝土造B/預鑄混凝土造T,加強磚造C,加強磚造C,加強磚造C,加強磚造C,鋼鐵造（不分面積）U.J,,木、石、磚造F.E.D.H.G,土、竹造K.L", "編號": 115, "第一層級": "花蓮縣政府"}, {"資料來源(部會單位)": "花蓮縣政府", "資料集名稱": "花蓮縣哺集乳室名單", "下載次數": "17", "瀏覽次數": "74", "主要欄位": "序號,公共場所名稱,地址,電話,開放時間", "編號": 116, "第一層級": "花蓮縣政府"}, {"資料來源(部會單位)": "花蓮縣政府", "資料集名稱": "花蓮縣戒菸服務合約醫事機構名單", "下載次數": "0", "瀏覽次數": "38", "主要欄位": "序號,醫事機構類別,醫事機構名稱,電話,郵遞區號,地址,給藥,衛教", "編號": 117, "第一層級": "花蓮縣政府"}, {"資料來源(部會單位)": "花蓮縣政府", "資料集名稱": "花蓮縣血壓站資訊", "下載次數": "2", "瀏覽次數": "43", "主要欄位": "編號,縣市,鄉鎮市,設站據點,地址,開放量血壓時間", "編號": 118, "第一層級": "花蓮縣政府"}, {"資料來源(部會單位)": "花蓮縣政府", "資料集名稱": "花蓮縣糖尿病共同照護網之醫療院所名單", "下載次數": "11", "瀏覽次數": "53", "主要欄位": "序號,醫事機構名稱,特約類別,地址,聯絡電話,備註", "編號": 119, "第一層級": "花蓮縣政府"}, {"資料來源(部會單位)": "花蓮縣政府", "資料集名稱": "花蓮縣流感疫苗合約院所", "下載次數": "3", "瀏覽次數": "48", "主要欄位": "十碼章,醫院名稱,縣市別,行政區,郵遞區號,地址,連絡電話,座標緯度,座標經度,備註", "編號": 120, "第一層級": "花蓮縣政府"}, {"資料來源(部會單位)": "花蓮縣政府", "資料集名稱": "花蓮縣卡介苗接種時間", "下載次數": "0", "瀏覽次數": "42", "主要欄位": "衛生所/醫院,期間,時間,備註", "編號": 121, "第一層級": "花蓮縣政府"}, {"資料來源(部會單位)": "花蓮縣政府", "資料集名稱": "花蓮縣公費流感合約院所名單", "下載次數": "2", "瀏覽次數": "45", "主要欄位": "編號,鄉鎮別,機構名稱,地址,聯絡電話,負責人,承辦人,合約狀態,單位醫事代碼", "編號": 122, "第一層級": "花蓮縣政府"}, {"資料來源(部會單位)": "花蓮縣政府", "資料集名稱": "花蓮縣通過食品衛生優良評鑑名單(GHP)", "下載次數": "4", "瀏覽次數": "61", "主要欄位": "序,業者名稱(市招/商登)、,地址,評核等級", "編號": 123, "第一層級": "花蓮縣政府"}, {"資料來源(部會單位)": "花蓮縣政府", "資料集名稱": "花蓮縣東大門國際觀光夜市通過食品衛生優良評鑑名單", "下載次數": "6", "瀏覽次數": "56", "主要欄位": "序,業者名稱,攤位編號", "編號": 124, "第一層級": "花蓮縣政府"}, {"資料來源(部會單位)": "花蓮縣政府", "資料集名稱": "花蓮縣街頭藝人展演空間場地(含公共空間)相關規範彙整表", "下載次數": "22", "瀏覽次數": "103", "主要欄位": "序號,單位,開放空間名稱,開放地區及範圍,聯絡窗口,聯絡電話,時段限制,音量限制,街頭藝人類型限制,街頭藝人人數限制,相關場地規範,其他注意事項", "編號": 125, "第一層級": "花蓮縣政府"}, {"資料來源(部會單位)": "花蓮縣政府", "資料集名稱": "花蓮縣公共圖書館一覽表", "下載次數": "28", "瀏覽次數": "150", "主要欄位": "序號,單位,電話,地址,休館日,備註", "編號": 126, "第一層級": "花蓮縣政府"}, {"資料來源(部會單位)": "花蓮縣政府", "資料集名稱": "花蓮縣公共藝術設置一覽表", "下載次數": "2", "瀏覽次數": "44", "主要欄位": "序,興辦機關,案名/作品名稱,徵選方式,件數,創作者,設置金額", "編號": 127, "第一層級": "花蓮縣政府"}, {"資料來源(部會單位)": "花蓮縣政府", "資料集名稱": "花蓮縣花蓮地政事務所轄區地段圖", "下載次數": "11", "瀏覽次數": "82", "主要欄位": "鄉市名,段名,段代碼,行政,管轄,分帶系統,圖籍種類,施測年度", "編號": 128, "第一層級": "花蓮縣政府"}, {"資料來源(部會單位)": "花蓮縣政府", "資料集名稱": "花蓮縣花蓮地政事務所不動產買賣案統計表", "下載次數": "25", "瀏覽次數": "117", "主要欄位": "年份,月份,件數,筆棟數", "編號": 129, "第一層級": "花蓮縣政府"}, {"資料來源(部會單位)": "花蓮縣政府", "資料集名稱": "花蓮縣花蓮地政事務所各鄉市買賣案統計表", "下載次數": "10", "瀏覽次數": "58", "主要欄位": "謝惠婷", "編號": 130, "第一層級": "花蓮縣政府"}, {"資料來源(部會單位)": "花蓮縣政府", "資料集名稱": "花蓮縣富里鄉人口統計資料", "下載次數": "13", "瀏覽次數": "148", "主要欄位": "年度,月份,總人口數,男性人口數,女姓人口數,山地原住民人口數,平地原住民人口數", "編號": 131, "第一層級": "花蓮縣政府"}, {"資料來源(部會單位)": "花蓮縣政府", "資料集名稱": "花蓮縣富里鄉戶籍登記(註記)案件及核發證明文件月統表", "下載次數": "0", "瀏覽次數": "41", "主要欄位": "總案件數,遷徙登記,身分登記,更正,變更,原住民身分認定及登記,分合戶,國民身分證,門牌,門牌證明,戶籍謄本,戶口名簿,印鑑", "編號": 132, "第一層級": "花蓮縣政府"}, {"資料來源(部會單位)": "花蓮縣政府", "資料集名稱": "花蓮縣富里鄉戶政管理及便民服務案件統計表", "下載次數": "2", "瀏覽次數": "39", "主要欄位": "年度,月份,戶政管理件數,便民服務件數", "編號": 133, "第一層級": "花蓮縣政府"}, {"資料來源(部會單位)": "花蓮縣政府", "資料集名稱": "花蓮縣環保旅店名單*", "下載次數": "43", "瀏覽次數": "117", "主要欄位": "項次,旅館名稱,電話,地址", "編號": 134, "第一層級": "花蓮縣政府"}, {"資料來源(部會單位)": "花蓮縣政府", "資料集名稱": "花蓮縣航空噪音防制區*", "下載次數": "8", "瀏覽次數": "53", "主要欄位": "本縣航空噪音防制區,噪音區間,區域範圍", "編號": 135, "第一層級": "花蓮縣政府"}, {"資料來源(部會單位)": "花蓮縣政府", "資料集名稱": "花蓮縣政府各年度公共債務數及每人負擔數", "下載次數": "11", "瀏覽次數": "51", "主要欄位": "各年度公共債務數及每人負擔數,1年以上非自償債務(億元)、,未滿1年債務(億元)、,債務合計(億元)、,平均每人債務負擔(萬元)、,自償性債務億元", "編號": 136, "第一層級": "花蓮縣政府"}, {"資料來源(部會單位)": "花蓮縣政府", "資料集名稱": "花蓮縣歷年人口統計表(最新)", "下載次數": "171", "瀏覽次數": "772", "主要欄位": "序號,年度,總戶數,總人口數,男性人數,女性人數,平地原住民,山地原住民", "編號": 137, "第一層級": "花蓮縣政府"}, {"資料來源(部會單位)": "花蓮縣政府", "資料集名稱": "花蓮縣各觀光遊憩區遊客人數統計(最新)", "下載次數": "120", "瀏覽次數": "397", "主要欄位": "月份,鯉魚潭,七星潭,太魯閣,秀姑巒溪遊客中心,海洋公園,石雕博物館,慶修院,松園別館,林田山,南安遊客中心,東大門夜市,親不知子天空古道,合計", "編號": 138, "第一層級": "花蓮縣政府"}, {"資料來源(部會單位)": "花蓮縣政府", "資料集名稱": "花蓮縣災害救助收容場所(最新)", "下載次數": "21", "瀏覽次數": "117", "主要欄位": "災民收容所編號,災民收容所名稱,所在鄉鎮市,聯絡人姓名,聯絡人電話,手機號碼,收容所管理單位,管理人姓名,管理人電話,管理人手機,郵遞區號,收容所縣市,收容所鄉鎮,收容所村里,收容所地址,服務里別,室內人數,室外人數,總共人數,適用災害別(水災)、,適用災害別(震災)、,適用災害別(土石流)、,適用災害別(海嘯)、,適用災害別(核子事故)、,適合避難弱者安置,處所特性別(室內)、,處所特性別(室外)", "編號": 139, "第一層級": "花蓮縣政府"}, {"資料來源(部會單位)": "花蓮縣政府", "資料集名稱": "花蓮縣居家護理機構清冊(最新)", "下載次數": "27", "瀏覽次數": "86", "主要欄位": "序號,型態別,機構名稱,地址,權屬別,電話", "編號": 140, "第一層級": "花蓮縣政府"}, {"資料來源(部會單位)": "花蓮縣政府", "資料集名稱": "花蓮縣心理健康小站一覽表(最新)", "下載次數": "9", "瀏覽次數": "69", "主要欄位": "名稱,地址", "編號": 141, "第一層級": "花蓮縣政府"}, {"資料來源(部會單位)": "花蓮縣政府", "資料集名稱": "花蓮縣多元繳稅方式件數統計表(最新)", "下載次數": "8", "瀏覽次數": "44", "主要欄位": "繳稅方式年度,金融機構繳稅,便利超商繳稅,自動櫃員機轉帳繳稅,長期約定轉帳繳稅,信用卡繳稅,電話語音轉帳繳稅,晶片金融卡網際網路轉帳繳稅,合計", "編號": 142, "第一層級": "花蓮縣政府"}, {"資料來源(部會單位)": "臺灣高等法院花蓮分院", "資料集名稱": "臺灣高等法院花蓮分院106年度12月份會計月報(XML)", "下載次數": "1", "瀏覽次數": "52", "主要欄位": "", "編號": 143, "第一層級": "花蓮縣政府"}, {"資料來源(部會單位)": "臺灣花蓮地方法院", "資料集名稱": "公告臺灣花蓮地方法院106年12月份會計月報(XML檔)", "下載次數": "3", "瀏覽次數": "55", "主要欄位": "", "編號": 144, "第一層級": "花蓮縣政府"}, {"資料來源(部會單位)": "花蓮縣政府", "資料集名稱": "花蓮縣花蓮地政事務所土地公告現值及公告地價", "下載次數": "57", "瀏覽次數": "440", "主要欄位": "行政區,段小段,地號(00010000地號為1地號、00010001地號為1-1地號)、,公告土地現值(元/㎡)、,公告地價(元/㎡)", "編號": 145, "第一層級": "花蓮縣政府"}, {"資料來源(部會單位)": "花蓮縣政府", "資料集名稱": "花蓮縣流感疫苗醫療院所名單", "下載次數": "11", "瀏覽次數": "112", "主要欄位": "十碼章,醫院名稱,縣市別,行政區,郵遞區號,地址,聯絡電話,座標緯度,座標經度,備註", "編號": 146, "第一層級": "花蓮縣政府"}, {"資料來源(部會單位)": "花蓮縣政府", "資料集名稱": "花蓮縣抗病毒藥劑醫療院所名單", "下載次數": "5", "瀏覽次數": "82", "主要欄位": "十碼章,醫院名稱,縣市別,行政區,郵遞區號,地址,聯絡電話,座標緯度,座標經度,備註", "編號": 147, "第一層級": "花蓮縣政府"}, {"資料來源(部會單位)": "臺灣高等法院花蓮分院", "資料集名稱": "臺灣高等法院花蓮分院107年度1月份會計月報(XML)", "下載次數": "1", "瀏覽次數": "33", "主要欄位": "", "編號": 148, "第一層級": "花蓮縣政府"}, {"資料來源(部會單位)": "臺灣花蓮地方法院", "資料集名稱": "公告臺灣花蓮地方法院107年1月份會計月報(XML檔)", "下載次數": "1", "瀏覽次數": "47", "主要欄位": "", "編號": 149, "第一層級": "花蓮縣政府"}, {"資料來源(部會單位)": "臺灣高等法院花蓮分院", "資料集名稱": "臺灣高等法院花蓮分院107年度法定預算(XML)", "下載次數": "13", "瀏覽次數": "43", "主要欄位": "", "編號": 150, "第一層級": "花蓮縣政府"}, {"資料來源(部會單位)": "臺灣花蓮地方法院", "資料集名稱": "公告臺灣花蓮地方法院107年度法定預算(XML檔)", "下載次數": "1", "瀏覽次數": "33", "主要欄位": "款、項、目、節、科目名稱、預算科目編號、人事費、業務費_經、奬補助費_經、債務費、預備金_經、經常支出小計、業務費_資、設備及投資、奬補助費_資、預備金_資、資本支出小計、合計、職能別分類經濟性分類、消費支出_經、債務利息_經、補助地方_經、移轉民間_經、小計_經、資本形成_資、土地購入_資、增資_資、補助地方_資、移轉民間_資、小計_資、總計", "編號": 151, "第一層級": "花蓮縣政府"}, {"資料來源(部會單位)": "臺灣高等法院花蓮分院", "資料集名稱": "臺灣高等法院花蓮分院107年度2月份會計月報(XML)", "下載次數": "1", "瀏覽次數": "37", "主要欄位": "會計年度、月份、款、項、目、節、預算年度、預算科目編號、預算科目名稱、細目編號、細目名稱、原預算數、追加減數、截至本月止累計分配數_1、本月實現數、截至本月止累計實現數_2、應收收入數_3、分配數預算餘額_4、分支計畫編號、分支計畫名稱、用途別編號、用途別名稱、第一預備金、第二預備金、經費流用數、預算調整數、應付數、已分配尚未執行數、備註_預暫付數、基金別、會計分類、使用機關別、科目分類、會計科目編號、會計科目名稱、金額、科目名稱、取得成本、以前年度累計折舊_長期投資評價、本年度資本資產成本變動_增加數、本年度資本資產成本變動_減少數、本年度累計折舊_長期投資評價變動數、期末帳面金額、備註、業務計畫或工作計畫、經資門、執行數、項目、收入實現數、減項_收入待納庫數、加項_以前年度待納庫繳庫數、加項_以前年度撥款於本年度繳還數_材料、加項_以前年度撥款於本年度繳還數_存出保證金、加項_以前年度撥款於本年度繳還數_其他應收款、加項_預收款、加項_剔除經費、繳付公庫數、一級用途別編號、一級用途別名稱、支出實現數、加項_預付款、加項_材料、加項_存出保證金、加項_零用金、加項_退還收入預收款、加項_其他應收款、減項_以前年度撥款於本年度實現數、公庫撥入數、公庫分配數餘額、金額_本月數、金額_累計數", "編號": 152, "第一層級": "花蓮縣政府"}, {"資料來源(部會單位)": "臺灣高等法院花蓮分院", "資料集名稱": "臺灣高等法院花蓮分院106年度單位決算(XML及PDF)", "下載次數": "9", "瀏覽次數": "42", "主要欄位": "", "編號": 153, "第一層級": "花蓮縣政府"}, {"資料來源(部會單位)": "臺灣花蓮地方法院", "資料集名稱": "公告臺灣花蓮地方法院107年2月份會計月報(XML檔)", "下載次數": "0", "瀏覽次數": "29", "主要欄位": "", "編號": 154, "第一層級": "花蓮縣政府"}, {"資料來源(部會單位)": "臺灣花蓮地方法院", "資料集名稱": "公告臺灣花蓮地方法院107年3月份會計月報(XML檔)", "下載次數": "0", "瀏覽次數": "34", "主要欄位": "", "編號": 155, "第一層級": "花蓮縣政府"}, {"資料來源(部會單位)": "臺灣高等法院花蓮分院", "資料集名稱": "臺灣高等法院花蓮分院107年度3月份會計月報(XML)", "下載次數": "1", "瀏覽次數": "28", "主要欄位": "", "編號": 156, "第一層級": "花蓮縣政府"}, {"資料來源(部會單位)": "法務部矯正署花蓮監獄", "資料集名稱": "矯正署花蓮監獄106年會計報告(按月)", "下載次數": "3", "瀏覽次數": "40", "主要欄位": "會計年度、月份、款、項、目、節、預算年度、預算科目編號、預算科目名稱、細目編號、細目名稱、原預算數、追加減數、截至本月止累計分配數_1、本月實現數、截至本月止累計實現數_2、應收收入數_3、分配數預算餘額_4、分支計畫編號、分支計畫名稱、用途別編號、用途別名稱、第一預備金、第二預備金、經費流用數、預算調整數、應付數、已分配尚未執行數、備註_預暫付數、基金別、會計分類、使用機關別、科目分類、會計科目編號、會計科目名稱、金額、科目名稱、取得成本、以前年度累計折舊_長期投資評價、本年度資本資產成本變動_增加數、本年度資本資產成本變動_減少數、本年度累計折舊_長期投資評價變動數、期末帳面金額、備註、業務計畫或工作計畫、經資門、執行數、項目、收入實現數、減項_收入待納庫數、加項_以前年度待納庫繳庫數、加項_以前年度撥款於本年度繳還數_材料、加項_以前年度撥款於本年度繳還數_存出保證金、加項_以前年度撥款於本年度繳還數_其他應收款、加項_預收款、加項_剔除經費、繳付公庫數、一級用途別編號、一級用途別名稱、支出實現數、加項_預付款、加項_材料、加項_存出保證金、加項_零用金、加項_退還收入預收款、加項_其他應收款、減項_以前年度撥款於本年度實現數、公庫撥入數、公庫分配數餘額、金額_本月數、金額_累計數", "編號": 157, "第一層級": "花蓮縣政府"}, {"資料來源(部會單位)": "法務部矯正署花蓮監獄", "資料集名稱": "矯正署花蓮監獄107年會計報告(按月)", "下載次數": "4", "瀏覽次數": "45", "主要欄位": "會計年度、月份、款、項、目、節、預算年度、預算科目編號、預算科目名稱、細目編號、細目名稱、原預算數、追加減數、截至本月止累計分配數_1、本月實現數、截至本月止累計實現數_2、應收收入數_3、分配數預算餘額_4、分支計畫編號、分支計畫名稱、用途別編號、用途別名稱、第一預備金、第二預備金、經費流用數、預算調整數、應付數、已分配尚未執行數、備註_預暫付數、基金別、會計分類、使用機關別、科目分類、會計科目編號、會計科目名稱、金額、科目名稱、取得成本、以前年度累計折舊_長期投資評價、本年度資本資產成本變動_增加數、本年度資本資產成本變動_減少數、本年度累計折舊_長期投資評價變動數、期末帳面金額、備註、業務計畫或工作計畫、經資門、執行數、項目、收入實現數、減項_收入待納庫數、加項_以前年度待納庫繳庫數、加項_以前年度撥款於本年度繳還數_材料、加項_以前年度撥款於本年度繳還數_存出保證金、加項_以前年度撥款於本年度繳還數_其他應收款、加項_預收款、加項_剔除經費、繳付公庫數、一級用途別編號、一級用途別名稱、支出實現數、加項_預付款、加項_材料、加項_存出保證金、加項_零用金、加項_退還收入預收款、加項_其他應收款、減項_以前年度撥款於本年度實現數、公庫撥入數、公庫分配數餘額、金額_本月數、金額_累計數", "編號": 158, "第一層級": "花蓮縣政府"}, {"資料來源(部會單位)": "臺灣高等檢察署花蓮檢察分署", "資料集名稱": "臺灣高等法院花蓮分院檢察署107年度會計報告", "下載次數": "11", "瀏覽次數": "49", "主要欄位": "會計年度、月份、款、項、目、節、預算年度、預算科目編號、預算科目名稱、細目編號、細目名稱、原預算數、追加減數、截至本月止累計分配數_1、本月實現數、截至本月止累計實現數_2、應收收入數_3、分配數預算餘額_4、分支計畫編號、分支計畫名稱、用途別編號、用途別名稱、第一預備金、第二預備金、經費流用數、預算調整數、應付數、已分配尚未執行數、備註_預暫付數、基金別、會計分類、使用機關別、科目分類、會計科目編號、會計科目名稱、金額、科目名稱、取得成本、以前年度累計折舊_長期投資評價、本年度資本資產成本變動_增加數、本年度資本資產成本變動_減少數、本年度累計折舊_長期投資評價變動數、期末帳面金額、備註、業務計畫或工作計畫、經資門、執行數、項目、收入實現數、減項_收入待納庫數、加項_以前年度待納庫繳庫數、加項_以前年度撥款於本年度繳還數_材料、加項_以前年度撥款於本年度繳還數_存出保證金、加項_以前年度撥款於本年度繳還數_其他應收款、加項_預收款、加項_剔除經費、繳付公庫數、一級用途別編號、一級用途別名稱、支出實現數、加項_預付款、加項_材料、加項_存出保證金、加項_零用金、加項_退還收入預收款、加項_其他應收款、減項_以前年度撥款於本年度實現數、公庫撥入數、公庫分配數餘額、金額_本月數、金額_累計數", "編號": 159, "第一層級": "花蓮縣政府"}, {"資料來源(部會單位)": "臺灣花蓮地方檢察署", "資料集名稱": "臺灣花蓮地方法院檢察署107年度會計報告", "下載次數": "3", "瀏覽次數": "20", "主要欄位": "會計年度、月份、款、項、目、節、預算年度、預算科目編號、預算科目名稱、細目編號、細目名稱、原預算數、追加減數、截至本月止累計分配數_1、本月實現數、截至本月止累計實現數_2、應收收入數_3、分配數預算餘額_4、分支計畫編號、分支計畫名稱、用途別編號、用途別名稱、第一預備金、第二預備金、經費流用數、預算調整數、應付數、已分配尚未執行數、備註_預暫付數、基金別、會計分類、使用機關別、科目分類、會計科目編號、會計科目名稱、金額", "編號": 160, "第一層級": "花蓮縣政府"}, {"資料來源(部會單位)": "臺灣花蓮地方法院", "資料集名稱": "公告臺灣花蓮地方法院106年度單位決算(XML檔)", "下載次數": "2", "瀏覽次數": "17", "主要欄位": "", "編號": 161, "第一層級": "花蓮縣政府"}, {"資料來源(部會單位)": "臺灣高等法院花蓮分院", "資料集名稱": "臺灣高等法院花蓮分院107年度4月份會計月報(XML)", "下載次數": "0", "瀏覽次數": "20", "主要欄位": "", "編號": 162, "第一層級": "花蓮縣政府"}, {"資料來源(部會單位)": "臺灣花蓮地方法院", "資料集名稱": "臺灣花蓮地方法院107年4月份會計月報", "下載次數": "0", "瀏覽次數": "18", "主要欄位": "", "編號": 163, "第一層級": "花蓮縣政府"}, {"資料來源(部會單位)": "臺灣高等法院花蓮分院", "資料集名稱": "臺灣高等法院花蓮分院107年度5月份會計月報(XML)", "下載次數": "0", "瀏覽次數": "30", "主要欄位": "", "編號": 164, "第一層級": "花蓮縣政府"}, {"資料來源(部會單位)": "臺灣花蓮地方法院", "資料集名稱": "臺灣花蓮地方法院107年5月份會計月報(XML檔)", "下載次數": "1", "瀏覽次數": "21", "主要欄位": "", "編號": 165, "第一層級": "花蓮縣政府"}, {"資料來源(部會單位)": "臺灣高等法院花蓮分院", "資料集名稱": "臺灣高等法院花蓮分院107年度6月份會計月報(XML)", "下載次數": "2", "瀏覽次數": "7", "主要欄位": "", "編號": 166, "第一層級": "花蓮縣政府"}, {"資料來源(部會單位)": "臺灣花蓮地方法院", "資料集名稱": "臺灣花蓮地方法院107年6月份會計月報(XML檔)", "下載次數": "2", "瀏覽次數": "11", "主要欄位": "", "編號": 167, "第一層級": "花蓮縣政府"}]